mm_mnemonic/__init__.py
mm_mnemonic/account.py
mm_mnemonic/cli.py
mm_mnemonic/crypto.py
mm_mnemonic/mnemonic.py
mm_mnemonic/network.py
mm_mnemonic/output.py
mm_mnemonic/passphrase.py
mm_mnemonic/types.py
mm_mnemonic/chains/__init__.py
mm_mnemonic/chains/btc.py
mm_mnemonic/chains/eth.py
mm_mnemonic/chains/sol.py
mm_mnemonic/chains/trx.py
mm_mnemonic/commands/__init__.py
mm_mnemonic/commands/derive.py
mm_mnemonic/commands/new.py
mm_mnemonic/commands/search.py
mm_mnemonic-0.1.3.dist-info/METADATA
mm_mnemonic-0.1.3.dist-info/WHEEL
mm_mnemonic-0.1.3.dist-info/entry_points.txt
mm_mnemonic-0.1.3.dist-info/RECORD
