Metadata-Version: 2.4
Name: mm-mnemonic
Version: 0.1.3
Requires-Python: >=3.12
Requires-Dist: base58==2.1.1
Requires-Dist: cryptography==45.0.3
Requires-Dist: ecdsa==0.19.1
Requires-Dist: eth-account==0.13.7
Requires-Dist: mnemonic==0.21
Requires-Dist: pynacl==1.5.0
Requires-Dist: tomlkit==0.13.2
Requires-Dist: typer==0.16.0
